gradslam/__init__.py
gradslam/version.py
gradslam/config/__init__.py
gradslam/config/cfgnode.py
gradslam/datasets/__init__.py
gradslam/datasets/datautils.py
gradslam/datasets/icl.py
gradslam/datasets/scannet.py
gradslam/datasets/tum.py
gradslam/datasets/tumutils.py
gradslam/geometry/__init__.py
gradslam/geometry/geometryutils.py
gradslam/geometry/projutils.py
gradslam/geometry/se3utils.py
gradslam/metrics/__init__.py
gradslam/odometry/__init__.py
gradslam/odometry/base.py
gradslam/odometry/gradicp.py
gradslam/odometry/groundtruth.py
gradslam/odometry/icp.py
gradslam/odometry/icputils.py
gradslam/slam/__init__.py
gradslam/slam/fusionutils.py
gradslam/slam/icpslam.py
gradslam/slam/pointfusion.py
gradslam/structures/__init__.py
gradslam/structures/pointclouds.py
gradslam/structures/rgbdimages.py
gradslam/structures/structutils.py
gradslam/structures/utils.py
gradslam/utils/__init__.py
tests/__init__.py
tests/common.py
tests/common_testing.py
gradslam-0.1.0.dist-info/LICENSE
gradslam-0.1.0.dist-info/METADATA
gradslam-0.1.0.dist-info/WHEEL
gradslam-0.1.0.dist-info/top_level.txt
gradslam-0.1.0.dist-info/zip-safe
gradslam-0.1.0.dist-info/RECORD
